printrun/gcoder_line.pyx
printrun/objectplater.py
printrun/zscaper.py
printrun/utils.py
printrun/gcoder_line_extra.h
printrun/stlview.py
printrun/eventhandler.py
printrun/gviz.py
printrun/printcore.py
printrun/stlplater.py
printrun/gcoder_line.c
printrun/__init__.py
printrun/device.py
printrun/injectgcode.py
printrun/pronterface.py
printrun/gcview.py
printrun/projectlayer.py
printrun/gcoder.py
printrun/gcodeplater.py
printrun/rpc.py
printrun/excluder.py
printrun/pronsole.py
printrun/settings.py
printrun/gcoder_line.cpython-311-i386-linux-gnu.so
printrun/packer.py
printrun/stltool.py
printrun/power/__init__.py
printrun/power/osx.py
printrun/spoolmanager/spoolmanager.py
printrun/spoolmanager/__init__.py
printrun/spoolmanager/spoolmanager_gui.py
printrun/gui/utils.py
printrun/gui/__init__.py
printrun/gui/log.py
printrun/gui/controls.py
printrun/gui/graph.py
printrun/gui/viz.py
printrun/gui/widgets.py
printrun/gui/bufferedcanvas.py
printrun/gui/xybuttons.py
printrun/gui/toolbar.py
printrun/gui/zbuttons.py
printrun/gl/panel.py
printrun/gl/__init__.py
printrun/gl/trackball.py
printrun/gl/libtatlin/actors.py
printrun/gl/libtatlin/__init__.py
printrun/plugins/sample.py
printrun/plugins/__init__.py
Printrun-2.2.0.dist-info/top_level.txt
Printrun-2.2.0.dist-info/RECORD
Printrun-2.2.0.dist-info/METADATA
Printrun-2.2.0.dist-info/COPYING
Printrun-2.2.0.dist-info/WHEEL
Printrun-2.2.0.data/scripts/printcore.py
Printrun-2.2.0.data/scripts/plater.py
Printrun-2.2.0.data/scripts/pronterface.py
Printrun-2.2.0.data/scripts/pronsole.py
Printrun-2.2.0.data/data/share/pixmaps/pronterface.png
Printrun-2.2.0.data/data/share/pixmaps/pronsole.png
Printrun-2.2.0.data/data/share/pixmaps/plater.png
Printrun-2.2.0.data/data/share/pronterface/images/control_z_mini.svg
Printrun-2.2.0.data/data/share/pronterface/images/inject.png
Printrun-2.2.0.data/data/share/pronterface/images/reset.png
Printrun-2.2.0.data/data/share/pronterface/images/arrow_keys.png
Printrun-2.2.0.data/data/share/pronterface/images/control_xy.png
Printrun-2.2.0.data/data/share/pronterface/images/zoom_out.png
