Metadata-Version: 2.1
Name: Printrun
Version: 2.2.0
Summary: Host software for 3D printers
Author: Kliment Yanev, Guillaume Seguin
Project-URL: Homepage, https://github.com/kliment/Printrun/
Project-URL: Issues, https://github.com/kliment/Printrun/issues
Project-URL: Changelog, https://github.com/kliment/Printrun/blob/master/NEWS.md
Classifier: Environment :: X11 Applications :: GTK
Classifier: Intended Audience :: End Users/Desktop
Classifier: Intended Audience :: Manufacturing
Classifier: Intended Audience :: Science/Research
Classifier: License :: OSI Approved :: GNU General Public License v3 or later (GPLv3+)
Classifier: Operating System :: MacOS :: MacOS X
Classifier: Operating System :: Microsoft :: Windows
Classifier: Operating System :: POSIX :: Linux
Classifier: Programming Language :: Python :: 3 :: Only
Classifier: Programming Language :: Python :: 3.8
Classifier: Programming Language :: Python :: 3.9
Classifier: Programming Language :: Python :: 3.10
Classifier: Programming Language :: Python :: 3.11
Classifier: Programming Language :: Python :: 3.12
Classifier: Programming Language :: Python :: 3.13
Classifier: Topic :: Printing
Requires-Python: >=3.8
License-File: COPYING
Requires-Dist: pyserial >=3.0
Requires-Dist: wxPython >=4.2.0
Requires-Dist: numpy >=1.8.2
Requires-Dist: pyglet <2.0,>=1.1
Requires-Dist: psutil >=2.1
Requires-Dist: lxml >=2.9.1
Requires-Dist: platformdirs
Requires-Dist: puremagic
Requires-Dist: pyobjc-framework-Cocoa ; sys_platform == "darwin"
Requires-Dist: dbus-python >=1.2.0 ; sys_platform == "linux"
Requires-Dist: pillow <10.0 ; sys_platform == "win32"
Requires-Dist: pyreadline3 ; sys_platform == "win32"
